[{"accountNumber":"10","accountBalance":10000.0,"creationDate":"10/06/2017","accountType":"current"},
{"accountNumber":"20","accountBalance":15000.0,"creationDate":"11/06/2017","accountType":"saving"},
{"accountNumber":"30","accountBalance":12000.0,"creationDate":"15/08/2017","accountType":"current"},
{"accountNumber":"40","accountBalance":11000.0,"creationDate":"10/02/2017","accountType":"saving"},
{"accountNumber":"50","accountBalance":14000.0,"creationDate":"18/01/2017","accountType":"current"},
{"accountNumber":"60","accountBalance":19000.0,"creationDate":"19/03/2017","accountType":"saving"},
{"accountNumber":"70","accountBalance":2000.00,"creationDate":"10/07/2017","accountType":"current"},
{"accountNumber":"80","accountBalance":21000.0,"creationDate":"01/06/2017","accountType":"saving"},
{"accountNumber":"90","accountBalance":28000.0,"creationDate":"18/11/2017","accountType":"current"},
{"accountNumber":"100","accountBalance":22000.0,"creationDate":"11/03/2017","accountType":"saving"},
{"accountNumber":"110","accountBalance":9000.0,"creationDate":"13/04/2017","accountType":"current"},
{"accountNumber":"120","accountBalance":8000.0,"creationDate":"28/09/2017","accountType":"saving"},
{"accountNumber":"130","accountBalance":9000.0,"creationDate":"05/01/2017","accountType":"current"},
{"accountNumber":"140","accountBalance":12000.0,"creationDate":"16/02/2017","accountType":"saving"},
{"accountNumber":"150","accountBalance":17000.0,"creationDate":"10/03/2017","accountType":"current"},
{"accountNumber":"160","accountBalance":13000.0,"creationDate":"17/09/2017","accountType":"saving"},
{"accountNumber":"170","accountBalance":12000.0,"creationDate":"09/07/2017","accountType":"current"},
{"accountNumber":"180","accountBalance":18000.0,"creationDate":"02/03/2017","accountType":"saving"},
{"accountNumber":"190","accountBalance":19000.0,"creationDate":"10/06/2017","accountType":"current"}]

